utils/__init__.py
utils/action_executor.py
utils/api_client.py
utils/screenshot.py
gemini_agent-0.1.0.dist-info/METADATA
gemini_agent-0.1.0.dist-info/WHEEL
gemini_agent-0.1.0.dist-info/entry_points.txt
gemini_agent-0.1.0.dist-info/top_level.txt
gemini_agent-0.1.0.dist-info/RECORD
